sedonadb/adbc.py
sedonadb/context.py
sedonadb/dataframe.py
sedonadb/datasource.py
sedonadb/dbapi.py
sedonadb/testing.py
sedonadb/udf.py
sedonadb/utility.py
sedonadb/_lib.cp313-win_amd64.pyd
sedonadb/_options.py
sedonadb/__init__.py
sedonadb-0.2.0.dist-info/DELVEWHEEL
sedonadb-0.2.0.dist-info/METADATA
sedonadb-0.2.0.dist-info/RECORD
sedonadb-0.2.0.dist-info/WHEEL
sedonadb.libs/abseil_dll-f98a3c4cd6299f160b67cbc03093c267.dll
sedonadb.libs/geos-2d15c97481ee791de2b282fae97cc956.dll
sedonadb.libs/geos_c-d50f7ef2a95fb6a905491f452f0eba5c.dll
sedonadb.libs/libcrypto-3-x64-c73f5980229f777487d24f6b2742eab6.dll
sedonadb.libs/msvcp140-a4c2229bdc2a2a630acdc095b4d86008.dll
