Metadata-Version: 2.4
Name: sedonadb
Version: 0.2.0
Classifier: Programming Language :: Rust
Classifier: Programming Language :: Python :: Implementation :: CPython
Classifier: Programming Language :: Python :: Implementation :: PyPy
Requires-Dist: adbc-driver-manager[dbapi] ; extra == 'test'
Requires-Dist: adbc-driver-postgresql ; extra == 'test'
Requires-Dist: datafusion ; extra == 'test'
Requires-Dist: duckdb ; extra == 'test'
Requires-Dist: geoarrow-pyarrow ; extra == 'test'
Requires-Dist: geopandas ; extra == 'test'
Requires-Dist: pandas ; extra == 'test'
Requires-Dist: polars ; extra == 'test'
Requires-Dist: pytest ; extra == 'test'
Requires-Dist: adbc-driver-manager[dbapi] ; extra == 'geopandas'
Requires-Dist: geoarrow-pyarrow ; extra == 'geopandas'
Requires-Dist: geopandas ; extra == 'geopandas'
Provides-Extra: test
Provides-Extra: geopandas
Requires-Python: >=3.9
